<?xml version="1.0" encoding="utf-8"?>
<Map>
	<State code="100" label="Ain" symbol="Ain"/>
	<State code="200" label="Aisne" symbol="Aisne"/>
	<State code="300" label="Allier" symbol="Allier"/>
	<State code="400" label="AlpesdeHauteProvence" symbol="AlpesdeHauteProvence"/>
	<State code="500" label="HautesAlpes" symbol="HautesAlpes"/>
	<State code="600" label="AlpesMaritimes" symbol="AlpesMaritimes"/>
	<State code="700" label="Ardèche" symbol="Ardèche"/>
	<State code="800" label="Ardennes" symbol="Ardennes"/>
	<State code="900" label="Ariège" symbol="Ariège"/>
	<State code="1000" label="Aube" symbol="Aube"/>
	<State code="1100" label="Aude" symbol="Aude"/>
	<State code="1200" label="Aveyron" symbol="Aveyron"/>
	<State code="1300" label="BouchesduRhône" symbol="BouchesduRhône"/>
	<State code="1400" label="Calvados" symbol="Calvados"/>
	<State code="1500" label="Cantal" symbol="Cantal"/>
	<State code="1600" label="Charente" symbol="Charente"/>
	<State code="1700" label="CharenteMaritime" symbol="CharenteMaritime"/>
	<State code="1800" label="Cher" symbol="Cher"/>
	<State code="1900" label="Corrèze" symbol="Corrèze"/>
	<State code="2000" label="CorseduSud" symbol="CorseduSud"/>
	<State code="2100" label="HauteCorse" symbol="HauteCorse"/>
	<State code="2200" label="CôtedOr" symbol="CôtedOr"/>
	<State code="2300" label="CôtesdArmor" symbol="CôtesdArmor"/>
	<State code="2400" label="Creuse" symbol="Creuse"/>
	<State code="2500" label="Dordogne" symbol="Dordogne"/>
	<State code="2600" label="Doubs" symbol="Doubs"/>
	<State code="2700" label="Drôme" symbol="Drôme"/>
	<State code="2800" label="Eure" symbol="Eure"/>
	<State code="2900" label="EureetLoir" symbol="EureetLoir"/>
	<State code="3000" label="Finistère" symbol="Finistère"/>
	<State code="3100" label="Gard" symbol="Gard"/>
	<State code="3200" label="HauteGaronne" symbol="HauteGaronne"/>
	<State code="3300" label="Gers" symbol="Gers"/>
	<State code="3400" label="Gironde" symbol="Gironde"/>
	<State code="3500" label="Hérault" symbol="Hérault"/>
	<State code="3600" label="ÎlleetVilaine" symbol="ÎlleetVilaine"/>
	<State code="3700" label="Indre" symbol="Indre"/>
	<State code="3800" label="IndreetLoire" symbol="IndreetLoire"/>
	<State code="3900" label="Isère" symbol="Isère"/>
	<State code="4000" label="Jura" symbol="Jura"/>
	<State code="4100" label="Landes" symbol="Landes"/>
	<State code="4200" label="LoiretCher" symbol="LoiretCher"/>
	<State code="4300" label="Loire" symbol="Loire"/>
	<State code="4400" label="HauteLoire" symbol="HauteLoire"/>
	<State code="4500" label="LoireAtlantique" symbol="LoireAtlantique"/>
	<State code="4600" label="Loiret" symbol="Loiret"/>
	<State code="4700" label="Lot" symbol="Lot"/>
	<State code="4800" label="LotetGaronne" symbol="LotetGaronne"/>
	<State code="4900" label="Lozère" symbol="Lozère"/>
	<State code="5000" label="MaineetLoire" symbol="MaineetLoire"/>
	<State code="5100" label="Manche" symbol="Manche"/>
	<State code="5200" label="Marne" symbol="Marne"/>
	<State code="5300" label="HauteMarne" symbol="HauteMarne"/>
	<State code="5400" label="Mayenne" symbol="Mayenne"/>
	<State code="5500" label="MeurtheetMoselle" symbol="MeurtheetMoselle"/>
	<State code="5600" label="Meuse" symbol="Meuse"/>
	<State code="5700" label="Morbihan" symbol="Morbihan"/>
	<State code="5800" label="Moselle" symbol="Moselle"/>
	<State code="5900" label="Nièvre" symbol="Nièvre"/>
	<State code="6000" label="Nord" symbol="Nord"/>
	<State code="6100" label="Oise" symbol="Oise"/>
	<State code="6200" label="Orne" symbol="Orne"/>
	<State code="6300" label="PasdeCalais" symbol="PasdeCalais"/>
	<State code="6400" label="PuydeDôme" symbol="PuydeDôme"/>
	<State code="6500" label="PyrénéesAtlantiques" symbol="PyrénéesAtlantiques"/>
	<State code="6600" label="HautesPyrénées" symbol="HautesPyrénées"/>
	<State code="6700" label="PyrénéesOrientales" symbol="PyrénéesOrientales"/>
	<State code="6800" label="BasRhin" symbol="BasRhin"/>
	<State code="6900" label="HautRhin" symbol="HautRhin"/>
	<State code="7000" label="Rhône" symbol="Rhône"/>
	<State code="7100" label="ValdOise" symbol="ValdOise"/>
	<State code="7200" label="HauteSaône" symbol="HauteSaône"/>
	<State code="7300" label="SaôneetLoire" symbol="SaôneetLoire"/>
	<State code="7400" label="ValdOise" symbol="ValdOise"/>
	<State code="7500" label="Savoie" symbol="Savoie"/>
	<State code="7600" label="HauteSavoie" symbol="HauteSavoie"/>
	<State code="7700" label="Paris" symbol="Paris"/>
	<State code="7800" label="SeineMaritime" symbol="SeineMaritime"/>
	<State code="7900" label="SeineetMarne" symbol="SeineetMarne"/>
	<State code="8000" label="Yvelines" symbol="Yvelines"/>
	<State code="8100" label="DeuxSèvres" symbol="DeuxSèvres"/>
	<State code="8200" label="Somme" symbol="Somme"/>
	<State code="8300" label="Tarn" symbol="Tarn"/>
	<State code="8400" label="TarnetGaronne" symbol="TarnetGaronne"/>
	<State code="8500" label="Var" symbol="Var"/>
	<State code="8600" label="Vaucluse" symbol="Vaucluse"/>
	<State code="8700" label="Vendée" symbol="Vendée"/>
	<State code="8800" label="Vienne" symbol="Vienne"/>
	<State code="8900" label="HauteVienne" symbol="HauteVienne"/>
	<State code="9000" label="Vosges" symbol="Vosges"/>
	<State code="9100" label="Yonne" symbol="Yonne"/>
	<State code="9200" label="TerritoiredeBelfort" symbol="TerritoiredeBelfort"/>
	<State code="9300" label="Essone" symbol="Essone"/>
	<State code="9400" label="HautsdeSeine" symbol="HautsdeSeine"/>
	<State code="9500" label="SeineSaintDenis" symbol="SeineSaintDenis"/>
	<State code="9600" label="ValdeMarne" symbol="ValdeMarne"/>
	<State code="9700" label="ValdOise" symbol="ValdOise"/>
	<State code="9800" label="Sarthe" symbol="Sarthe"/>
</Map>